onefuzztypes/__init__.py
onefuzztypes/__version__.py
onefuzztypes/_monkeypatch.py
onefuzztypes/consts.py
onefuzztypes/enums.py
onefuzztypes/events.py
onefuzztypes/job_templates.py
onefuzztypes/models.py
onefuzztypes/primitives.py
onefuzztypes/py.typed
onefuzztypes/requests.py
onefuzztypes/responses.py
onefuzztypes/validators.py
onefuzztypes/webhooks.py
tests/__init__.py
tests/test_alnum_filter.py
tests/test_instance_config_update.py
tests/test_models.py
onefuzztypes-9.0.0.dist-info/LICENSE
onefuzztypes-9.0.0.dist-info/METADATA
onefuzztypes-9.0.0.dist-info/WHEEL
onefuzztypes-9.0.0.dist-info/top_level.txt
onefuzztypes-9.0.0.dist-info/RECORD
