Metadata-Version: 2.1
Name: onefuzztypes
Version: 9.0.0
Summary: Onefuzz Types Library
Home-page: https://github.com/microsoft/onefuzz/
Author: Microsoft Corporation
Author-email: fuzzing@microsoft.com
License: MIT
License-File: LICENSE
Requires-Dist: pydantic ==1.8.2
